dolfiny/__init__.py
dolfiny/continuation.py
dolfiny/expression.py
dolfiny/function.py
dolfiny/interpolation.py
dolfiny/invariants.py
dolfiny/io.py
dolfiny/la.py
dolfiny/localsolver.h
dolfiny/localsolver.py
dolfiny/mesh.py
dolfiny/odeint.py
dolfiny/projection.py
dolfiny/restriction.py
dolfiny/slepcblockproblem.py
dolfiny/snesblockproblem.py
dolfiny/utils.py
dolfiny-0.9.0.dist-info/METADATA
dolfiny-0.9.0.dist-info/WHEEL
dolfiny-0.9.0.dist-info/top_level.txt
dolfiny-0.9.0.dist-info/RECORD
