Metadata-Version: 2.1
Name: dolfiny
Version: 0.9.0
Summary: High-level and convenience wrappers for DOLFINx, the FEniCS library.
Author-email: Andreas Zilian <andreas.zilian@uni.lu>, Michal Habera <michal.habera@gmail.com>
Project-URL: repository, https://github.com/fenics-dolfiny/dolfiny
Requires-Python: >=3.10.0
Requires-Dist: fenics-dolfinx<0.10.0,>=0.9.0
Provides-Extra: all
Requires-Dist: dolfiny[demo,dev,test]; extra == "all"
Provides-Extra: demo
Requires-Dist: dolfiny[jit,vis]; extra == "demo"
Provides-Extra: dev
Requires-Dist: mypy<1.10; extra == "dev"
Requires-Dist: ruff; extra == "dev"
Provides-Extra: jit
Requires-Dist: numba; extra == "jit"
Requires-Dist: cppyy>=3.1.0; extra == "jit"
Provides-Extra: test
Requires-Dist: dolfiny[jit,vis]; extra == "test"
Requires-Dist: pytest-xdist; extra == "test"
Requires-Dist: scipy; extra == "test"
Provides-Extra: vis
Requires-Dist: matplotlib; extra == "vis"
Requires-Dist: pyvista>=0.43.0; extra == "vis"
